ZkIPYNBrenderer/__init__.py
ZkIPYNBrenderer/custom_exception.py
ZkIPYNBrenderer/logger.py
ZkIPYNBrenderer/site.py
ZkIPYNBrenderer/youtube.py
ZkIPYNBrenderer-0.0.8.dist-info/LICENSE
ZkIPYNBrenderer-0.0.8.dist-info/METADATA
ZkIPYNBrenderer-0.0.8.dist-info/WHEEL
ZkIPYNBrenderer-0.0.8.dist-info/top_level.txt
ZkIPYNBrenderer-0.0.8.dist-info/RECORD
